disnake/__init__.py
disnake/__main__.py
disnake/abc.py
disnake/activity.py
disnake/app_commands.py
disnake/appinfo.py
disnake/application_role_connection.py
disnake/asset.py
disnake/audit_logs.py
disnake/automod.py
disnake/backoff.py
disnake/bans.py
disnake/channel.py
disnake/client.py
disnake/colour.py
disnake/components.py
disnake/context_managers.py
disnake/custom_warnings.py
disnake/embeds.py
disnake/emoji.py
disnake/entitlement.py
disnake/enums.py
disnake/errors.py
disnake/file.py
disnake/flags.py
disnake/gateway.py
disnake/guild.py
disnake/guild_preview.py
disnake/guild_scheduled_event.py
disnake/http.py
disnake/i18n.py
disnake/integrations.py
disnake/invite.py
disnake/iterators.py
disnake/member.py
disnake/mentions.py
disnake/message.py
disnake/mixins.py
disnake/object.py
disnake/oggparse.py
disnake/onboarding.py
disnake/opus.py
disnake/partial_emoji.py
disnake/permissions.py
disnake/player.py
disnake/poll.py
disnake/py.typed
disnake/raw_models.py
disnake/reaction.py
disnake/role.py
disnake/shard.py
disnake/sku.py
disnake/soundboard.py
disnake/stage_instance.py
disnake/state.py
disnake/sticker.py
disnake/subscription.py
disnake/team.py
disnake/template.py
disnake/threads.py
disnake/user.py
disnake/utils.py
disnake/voice_client.py
disnake/voice_region.py
disnake/welcome_screen.py
disnake/widget.py
disnake/bin/COPYING
disnake/bin/libopus-0.x64.dll
disnake/bin/libopus-0.x86.dll
disnake/ext/commands/__init__.py
disnake/ext/commands/_types.py
disnake/ext/commands/base_core.py
disnake/ext/commands/bot.py
disnake/ext/commands/bot_base.py
disnake/ext/commands/cog.py
disnake/ext/commands/common_bot_base.py
disnake/ext/commands/context.py
disnake/ext/commands/converter.py
disnake/ext/commands/cooldowns.py
disnake/ext/commands/core.py
disnake/ext/commands/ctx_menus_core.py
disnake/ext/commands/custom_warnings.py
disnake/ext/commands/errors.py
disnake/ext/commands/flag_converter.py
disnake/ext/commands/flags.py
disnake/ext/commands/help.py
disnake-2.11.0.dist-info/LICENSE
disnake-2.11.0.dist-info/METADATA
disnake-2.11.0.dist-info/WHEEL
disnake-2.11.0.dist-info/top_level.txt
disnake-2.11.0.dist-info/RECORD
