Metadata-Version: 2.1
Name: disnake
Version: 2.11.0
Summary: A Python wrapper for the Discord API
Author: Disnake Development
License: MIT
Project-URL: Changelog, https://docs.disnake.dev/page/whats_new.html
Project-URL: Documentation, https://docs.disnake.dev/
Project-URL: Repository, https://github.com/DisnakeDev/disnake
Keywords: disnake,discord,discord api
Classifier: Development Status :: 5 - Production/Stable
Classifier: License :: OSI Approved :: MIT License
Classifier: Intended Audience :: Developers
Classifier: Natural Language :: English
Classifier: Operating System :: OS Independent
Classifier: Programming Language :: Python :: 3.8
Classifier: Programming Language :: Python :: 3.9
Classifier: Programming Language :: Python :: 3.10
Classifier: Programming Language :: Python :: 3.11
Classifier: Programming Language :: Python :: 3.12
Classifier: Programming Language :: Python :: 3.13
Classifier: Topic :: Internet
Classifier: Topic :: Software Development :: Libraries
Classifier: Topic :: Software Development :: Libraries :: Python Modules
Classifier: Topic :: Utilities
Classifier: Typing :: Typed
Requires-Python: >=3.8
License-File: LICENSE
Requires-Dist: aiohttp <4.0,>=3.7.0
Requires-Dist: typing-extensions >=4.1
Provides-Extra: docs
Requires-Dist: sphinx ==7.0.1 ; extra == 'docs'
Requires-Dist: sphinxcontrib-trio ~=1.1.2 ; extra == 'docs'
Requires-Dist: sphinx-hoverxref ==1.3.0 ; extra == 'docs'
Requires-Dist: sphinx-autobuild ~=2021.3 ; extra == 'docs'
Requires-Dist: sphinxcontrib-towncrier ==0.3.2a0 ; extra == 'docs'
Requires-Dist: towncrier ==23.6.0 ; extra == 'docs'
Requires-Dist: sphinx-notfound-page ==0.8.3 ; extra == 'docs'
Requires-Dist: sphinxext-opengraph ==0.9.1 ; extra == 'docs'
Provides-Extra: speed
Requires-Dist: orjson ~=3.6 ; extra == 'speed'
Requires-Dist: aiodns >=1.1 ; extra == 'speed'
Requires-Dist: Brotli ; extra == 'speed'
Requires-Dist: cchardet ; (python_version < "3.10") and extra == 'speed'
Provides-Extra: voice
Requires-Dist: PyNaCl <1.6,>=1.5.0 ; extra == 'voice'
Requires-Dist: audioop-lts ==0.2.1 ; (python_version >= "3.13") and extra == 'voice'
